python_loovpay/__init__.py
python_loovpay/src/__init__.py
python_loovpay/src/exceptions.py
python_loovpay/src/python_loovpay.py
python_loovpay/test/__init__.py
python_loovpay-0.0.1.dist-info/LICENSE
python_loovpay-0.0.1.dist-info/METADATA
python_loovpay-0.0.1.dist-info/WHEEL
python_loovpay-0.0.1.dist-info/top_level.txt
python_loovpay-0.0.1.dist-info/RECORD
