Metadata-Version: 2.1
Name: python-loovpay
Version: 0.0.1
Summary: LoovPay SDK for Python
Home-page: https://github.com/Mounir-Holding-Tech/LoovPay-Python-SDK.git
Author: Dada Leonardo
Author-email: dadaleonardo00@gmail.com
License: MIT
Keywords: python,loovpay,LoovPay,loov,python-loovpay,loovpay-python-sdk,loov-solutions,api-payment,mobile-payment,sdk,payment
Classifier: License :: OSI Approved :: MIT License
Classifier: Programming Language :: Python :: 3.10
Classifier: Operating System :: OS Independent
Requires-Python: >=3.10
License-File: LICENSE
Requires-Dist: requests >=2.0
Provides-Extra: dev
Requires-Dist: pytest >=7.0 ; extra == 'dev'
Requires-Dist: twine >=4.0.2 ; extra == 'dev'
